MANIFEST.in
README.md
requirements.txt
setup.py
bitproto_language_server/__init__.py