Metadata-Version: 2.1
Name: bitproto-language-server
Version: 1.2.2
Summary: Language server for bitproto
Home-page: https://github.com/hit9/bitproto
Author: Chao Wang
Author-email: hit9@icloud.com
Requires-Python: >=3.9
